cmdbase_vmware/__init__.py
cmdbase_vmware/__main__.py
cmdbase_vmware/_version.py
cmdbase_vmware/commands.py
cmdbase_vmware/commons.py
cmdbase_vmware/datastore.py
cmdbase_vmware/dump.py
cmdbase_vmware/host.py
cmdbase_vmware/inventory.py
cmdbase_vmware/license.py
cmdbase_vmware/utils.py
cmdbase_vmware/vm.py
cmdbase_vmware-0.0.1a2.dist-info/METADATA
cmdbase_vmware-0.0.1a2.dist-info/WHEEL
cmdbase_vmware-0.0.1a2.dist-info/entry_points.txt
cmdbase_vmware-0.0.1a2.dist-info/license.py
cmdbase_vmware-0.0.1a2.dist-info/top_level.txt
cmdbase_vmware-0.0.1a2.dist-info/RECORD
